tarea_3/src/rtl/Collaterals.v
/*
	Collaterals.v
		Defines two modules:
			Data_Path
			Counter
*/

////////////////////////////////////////////////////////////////////
//// Module: Data_Path
////////////////////////////////////////////////////////////////////

module Data_Path
(
	input	wire	[31:0]	iData_A, 		// Input data A  
	input	wire	[31:0]	iData_B,		// Input data B
	input 	wire	        iData_Reset,	// 
	input	wire 			Clock,			// 
	output	reg		[31:0]	oProduct		// 
);

// Registers Definition
reg [31:0] reg_B;
reg [31:0] reg_A;

// Define a Sum Result
reg [31:0] wTmp_Sum;
wire add_sel;
assign add_sel = reg_B[0];

always @ (posedge Clock) 
	begin
		wTmp_Sum = (!add_sel) ? oProduct : (oProduct + reg_A);
		oProduct = (iData_Reset) ? 32'b0   : wTmp_Sum ;
		reg_B 	 = (iData_Reset) ? iData_B : (reg_B >> 1);
		reg_A 	 = (iData_Reset) ? iData_A : (reg_A << 1);	
	end


endmodule
////////////////////////////////////////////////////////////////////

////////////////////////////////////////////////////////////////////
//// Module: Counter
////////////////////////////////////////////////////////////////////

module Counter # (parameter SIZE=5)
(
	input wire Clock, iCounterReset,
	output reg [SIZE-1:0] oCounter
);

// Counter logic
always @(posedge Clock )
	begin	
		// Synchronous Reset 
		if (iCounterReset)
			oCounter = 0;
		else
			begin
				oCounter = oCounter + 1;
			end			
	end

endmodule
////////////////////////////////////////////////////////////////////

tarea_3/src/rtl/Mult_Controller.v
`include "Collaterals.v"


////////////////////////////////////////////////////////////////////
//// STATES DEFINITIONS

`define		STATE_RESET		2'd0
`define		STATE_IDLE		2'd1
`define		STATE_MULT		2'd2
`define		STATE_DONE		2'd3

/////////////////////////////////////////////////////////////////////////
//// Module: Multiplicator                                           ////
/////////////////////////////////////////////////////////////////////////

module Multiplicator
(
	input	wire	[31:0]	iData_A, 	// 	Input data A  
	input	wire	[31:0]	iData_B,	// 	Input data B
	input 	wire	Clock,
	input 	wire	Reset,
	input 	wire 	iValid_Data,		// 	Input flag that 
	input	wire	iAcknoledged,		//	Input flaf that 
	output	reg		oDone,				//	Output flag that indicates when the data is ready 
	output	reg		oIdle,				//	Output flag that indicates when the data is ready
	output	wire 	[31:0]	oResult
);

/////////////////////////////////////////////////////////////////////////
reg  [1:0] 	rCurrentState;
reg  [1:0] 	rNextState;
reg		  	rData_Select;
reg 		rData_Reset;
/////////////////////////////////////////////////////////////////////////


// = = = = = = = = = = = = = = = = = = = = = = = = = = = = = = = = = = //
// Counter Instance                                                    //
// = = = = = = = = = = = = = = = = = = = = = = = = = = = = = = = = = = //
wire [4:0] wCounter;
reg	  rCounterReset;

Counter Counter_32b
(
	.Clock(Clock),
	.iCounterReset(rCounterReset),
	.oCounter(wCounter)
);

// = = = = = = = = = = = = = = = = = = = = = = = = = = = = = = = = =


// = = = = = = = = = = = = = = = = = = = = = = = = = = = = = = = = = = //
// Data_Path Instance                                                  //
// = = = = = = = = = = = = = = = = = = = = = = = = = = = = = = = = = = //
Data_Path DataPath
(
	.iData_A(iData_A), 			// Input data A  
	.iData_B(iData_B),			// Input data B
	.iData_Reset(rData_Reset),	// 
	.Clock(Clock),
	.oProduct(oResult)
);
// = = = = = = = = = = = = = = = = = = = = = = = = = = = = = = = = = = //

/////////////////////////////////////////////////////////////////////////
/*
	NEXT STATE LOGIC:
		Manage next state logic (rNextState becames rCurrentState).
		And reset state machine
*/
always @ (posedge Clock)
	begin
		// Synchornous Reset
		if(Reset)
			rCurrentState = `STATE_RESET; 	// Move to reset state if Reset signal
		else
			rCurrentState = rNextState; 	// Change Current State
	end
/////////////////////////////////////////////////////////////////////////


/////////////////////////////////////////////////////////////////////////
/*
	CONTROLLER STATE MACHINE.
		Consists of 4 states (therefore the 2 bit state registers).
			- STATE RESET
			- STATE IDLE
			- STATE MULT
			- STATE DONE

*/
always @ ( * )
	begin
		case (rCurrentState)
			/* 
				STATE RESET:
					
					State that resets (defines) the signals in the counter
					and the Data_Path.
			*/
			`STATE_RESET:
				begin
					rNextState = `STATE_IDLE; 	// Move on to IDLE state
					rData_Reset  = 1;			// Reset Data
					rCounterReset = 1;			// Reset Counter
					oDone = 0;					// Define oDone
					oIdle = 0;					// Define oIdle
				end
			/*
				STATE_IDLE:
					
					We are waiting for valid data. We reset counter and 
					data in the data path. Set oIdle flag up to comunicate
					that we are ready to receive data
			*/
			`STATE_IDLE:
				begin
					rNextState = (iValid_Data) ? `STATE_MULT : `STATE_IDLE ;
					rCounterReset = 1;	// 	Reset Counter for next state
					rData_Reset  = 1;	// 	Keep charging new data
					oDone = 0;			// 	Not even close to been close
					oIdle = 1;			//	We are Idle
				end
			/*
				STATE_MULT:
					
					In here most of the work is done by the Data_Path. By
					leaving the rData_Reset in 0, and waiting exactly 32 
					cycles.
					
					When we reach the 32 bit cycles. We move on to DONE 
					state
			*/
			`STATE_MULT:
				begin
					rNextState = (wCounter == 5'd31) ? `STATE_DONE : `STATE_MULT;
					rData_Reset = (wCounter == 5'd0) ? 1: 0; 		// No reset of data except on first run
					rCounterReset = 0;		// No reset of counter
					oDone = 0;				// Not Done
					oIdle = 0;				// Not Idle
				end
			/*
				STATE_DONE:
					
					We have the product ready. We send a oDone flag, to 
					comunicate that we already have the result and then 
					we check the iAcknoledged flag to move on to a IDLE
					state.
					
					Important to hold rData_Reset in 0, so result doesnt
					change 
			*/
			`STATE_DONE:
				begin
					rNextState = (iAcknoledged) ? `STATE_IDLE : `STATE_DONE;
					rData_Reset = 0; 	// This is so we maintain the exit
					rCounterReset = 1;	// No need to count 
					oDone = 1;			// We are done
					oIdle = 0;			// Not done
				end
		endcase
	end
endmodule
/////////////////////////////////////////////////////////////////////////

tarea_3/src/rtl/TestBench.v
`include "Mult_Controller.v"

module TestBench;
	// Signals definition
	reg Clock;
	reg Reset;
	reg [31:0] A;
	reg [31:0] B;
	reg Valid_Data_Flag, Ack_Flag;
	wire Done, Idle;
	wire [31:0] Result;

	//Clock definition 
	always
	  begin
	    if (Clock)
		  #5 Clock =  0;
		else
		  #5 Clock = 1;
	  end
	
		//Unit Under Test (Multiplicador) instance
	
	Multiplicator uut
	(
		.iData_A(A),
		.iData_B(B),	
		.Clock(Clock),
		.Reset(Reset),
		.iValid_Data(Valid_Data_Flag),	
		.iAcknoledged(Ack_Flag),		 
		.oDone(Done),				
		.oIdle(Idle),				
		.oResult(Result)
	);
	
	
	always @ (posedge Done)
	begin
		# 50 Ack_Flag = 1;	
	end
	

	always @ (negedge Done)
	begin
		# 50  Ack_Flag = 0;	
	end
		
	always @ (posedge Idle)
	begin
		//A <= $unsigned($random) %10;
		//B <= $unsigned($random) %10;
		A<=A+1;
		B<=B+1;
		# 500 Valid_Data_Flag <= 1;
		# 100 Valid_Data_Flag <= 0;	
	end
	
	initial 
	begin
	  // GTKwave
	  $dumpfile("Waves.vcd");
	  $dumpvars;
	  
	  // Inicializar señales primarias
	  #5 Clock = 0;
         Reset = 0;
         Ack_Flag = 0;
         Valid_Data_Flag = 0; 
         A = 1; 
		 B = 1;
	  // Hacer un reset para iniciar el conteo
	  #15 Reset = 1;
	  #80 Reset = 0;
        
	  #5000 $finish;                                                                                            

	end
	
	
endmodule

tarea_3/src/rtl/Waves.vcd
$date
	Mon May 11 21:16:44 2015
$end
$version
	Icarus Verilog
$end
$timescale
	1s
$end
$scope module TestBench $end
$var wire 1 ! Done $end
$var wire 1 " Idle $end
$var wire 32 # Result [31:0] $end
$var reg 32 $ A [31:0] $end
$var reg 1 % Ack_Flag $end
$var reg 32 & B [31:0] $end
$var reg 1 ' Clock $end
$var reg 1 ( Reset $end
$var reg 1 ) Valid_Data_Flag $end
$scope module uut $end
$var wire 1 * Clock $end
$var wire 1 + Reset $end
$var wire 1 , iAcknoledged $end
$var wire 32 - iData_A [31:0] $end
$var wire 32 . iData_B [31:0] $end
$var wire 1 / iValid_Data $end
$var wire 32 0 oResult [31:0] $end
$var wire 5 1 wCounter [4:0] $end
$var reg 1 2 oDone $end
$var reg 1 3 oIdle $end
$var reg 1 4 rCounterReset $end
$var reg 2 5 rCurrentState [1:0] $end
$var reg 1 6 rData_Reset $end
$var reg 2 7 rNextState [1:0] $end
$scope module Counter_32b $end
$var wire 1 * Clock $end
$var wire 1 8 iCounterReset $end
$var reg 5 9 oCounter [4:0] $end
$upscope $end
$scope module DataPath $end
$var wire 1 * Clock $end
$var wire 1 : add_sel $end
$var wire 32 ; iData_A [31:0] $end
$var wire 32 < iData_B [31:0] $end
$var wire 1 = iData_Reset $end
$var reg 32 > oProduct [31:0] $end
$var reg 32 ? reg_A [31:0] $end
$var reg 32 @ reg_B [31:0] $end
$var reg 32 A wTmp_Sum [31:0] $end
$upscope $end
$upscope $end
$upscope $end
$enddefinitions $end
#0
$dumpvars
bx A
bx @
bx ?
bx >
x=
bx <
bx ;
x:
bx 9
x8
bx 7
x6
bx 5
x4
x3
x2
bx 1
bx 0
x/
bx .
bx -
x,
x+
x*
x)
x(
x'
bx &
x%
bx $
bx #
x"
x!
$end
#5
b0xxxxxxxxxxxxxxxxxxxxxxxxxxxxxxx @
b1 &
b1 .
b1 <
b1 $
b1 -
b1 ;
0)
0/
0%
0,
0(
0+
0'
0*
#15
b0xxxxxxxxxxxxxxxxxxxxxxxxxxxxxx @
1'
1*
#20
0'
0*
1(
1+
#25
03
0"
02
0!
14
18
16
1=
b1 7
b0xxxxxxxxxxxxxxxxxxxxxxxxxxxxx @
b0 5
1'
1*
#30
0'
0*
#35
1:
b1 ?
b1 @
b0 >
b0 #
b0 0
b0 9
b0 1
1'
1*
#40
0'
0*
#45
b1 A
1'
1*
#50
0'
0*
#55
1'
1*
#60
0'
0*
#65
1'
1*
#70
0'
0*
#75
1'
1*
#80
0'
0*
#85
1'
1*
#90
0'
0*
#95
1'
1*
#100
0'
0*
0(
0+
#105
b10 &
b10 .
b10 <
b10 $
b10 -
b10 ;
13
1"
b1 5
1'
1*
#110
0'
0*
#115
0:
b10 ?
b10 @
1'
1*
#120
0'
0*
#125
b0 A
1'
1*
